Metadata-Version: 2.1
Name: craiyon.py
Version: 1.2.0
Summary: API Wrapper for craiyon.com (DAL-E-MINI). Generate awesome images from text tokens.
Home-page: https://github.com/FireHead90544/craiyon.py
Author: Rudransh Joshi
Author-email: rudranshjoshi1806@gmail.com
License: Apache License 2.0
Project-URL: Issue tracker, https://github.com/FireHead90544/craiyon.py/issues
Platform: any
License-File: LICENSE
